qbit_py_sdk/__init__.py
qbit_py_sdk/qbitClient.py
qbit_py_sdk/qbit_response.py
qbit_py_sdk/qbit_response_content.py
qbit_py_sdk/dto/__init__.py
qbit_py_sdk/dto/access_token_output.py
qbit_py_sdk/dto/code_output.py
qbit_py_sdk/dto/refresh_token_output.py
qbit_py_sdk/service/__init__.py
qbit_py_sdk/utils/__init__.py
qbit_py_sdk/utils/crypto_util.py
qbit_py_sdk-1.0.0.dist-info/LICENSE
qbit_py_sdk-1.0.0.dist-info/METADATA
qbit_py_sdk-1.0.0.dist-info/WHEEL
qbit_py_sdk-1.0.0.dist-info/top_level.txt
qbit_py_sdk-1.0.0.dist-info/RECORD
