Metadata-Version: 2.1
Name: qbit-py-sdk
Version: 1.0.0
Summary: qbit bass api 接口支持
Home-page: https://github.com/klover2/qbit-python-sdk
Author: qbit team
Author-email: w.klover@foxmail.com
Keywords: qbit,全球账户,量子卡
Classifier: Programming Language :: Python :: 3
Classifier: License :: OSI Approved :: Apache Software License
Classifier: Operating System :: OS Independent
Requires-Python: >=3.7
License-File: LICENSE
Requires-Dist: requests (>=2.28.1)
